ethermine/__init__.py
ethermine/__main__.py
ethermine/ethermine.py
ethermine/utils.py
ethermine_cli-1.2.0.dist-info/METADATA
ethermine_cli-1.2.0.dist-info/WHEEL
ethermine_cli-1.2.0.dist-info/entry_points.txt
ethermine_cli-1.2.0.dist-info/top_level.txt
ethermine_cli-1.2.0.dist-info/RECORD
